core/__init__.py
core/ascii_converter.py
core/ascii_displayer.py
core/ascii_file_encoding.py
core/audio_player.py
core/generate_color_ramp.py
core/utils.py
core/video_ascii_video.py
core/video_extractor.py
pdasc/__init__.py
pdasc/main.py
pdasc/fonts/CascadiaMono.ttf
pdasc/fonts/font8x8.ttf
pdasc/shaders/ascii.frag
pdasc-0.1.2.dist-info/licenses/LICENSE
web/__init__.py
web/image_controller/__init__.py
web/image_controller/app.py
web/image_controller/templates/index.html
web/video_player/__init__.py
web/video_player/app.py
web/video_player/templates/index.html
pdasc-0.1.2.dist-info/METADATA
pdasc-0.1.2.dist-info/WHEEL
pdasc-0.1.2.dist-info/entry_points.txt
pdasc-0.1.2.dist-info/top_level.txt
pdasc-0.1.2.dist-info/RECORD
