Metadata-Version: 2.4
Name: PDASC
Version: 0.1.2
Summary: Made for Intersession 2026
Author-email: Colin Politi <urboycolinthepanda@gmail.com>
License: MIT License
Project-URL: homepage, https://github.com/ColinThePanda/PDASC
Project-URL: Bug_Tracker, https://github.com/ColinThePanda/PDASC/issues
Classifier: Programming Language :: Python :: 3
Classifier: License :: OSI Approved :: MIT License
Classifier: Operating System :: OS Independent
Requires-Python: >=3.10
License-File: LICENSE
Requires-Dist: numpy>=2.4.1
Requires-Dist: Pillow>=12.1.0
Requires-Dist: numba>=0.63.1
Requires-Dist: pyaudio>=0.2.14
Requires-Dist: opencv-python>=4.12.0.88
Requires-Dist: zstandard>=0.25.0
Requires-Dist: flask>=3.1.2
Requires-Dist: moderngl>=5.12.0
Dynamic: license-file
